{
"type": "FeatureCollection",
"name": "CAERP_23",
"crs": { "type": "name", "properties": { "name": "urn:ogc:def:crs:OGC:1.3:CRS84" } },
"features": [
{ "type": "Feature", "properties": { "osm_id": 13340693783, "name": null, "amenity": "bench", "man_made": null, "leisure": null, "playground": null, "memorial": null }, "geometry": { "type": "Point", "coordinates": [ -3.2238563, 51.6766498 ] } },
{ "type": "Feature", "properties": { "osm_id": 13300636687, "name": null, "amenity": "bench", "man_made": null, "leisure": null, "playground": null, "memorial": null }, "geometry": { "type": "Point", "coordinates": [ -3.2265523, 51.683806 ] } },
{ "type": "Feature", "properties": { "osm_id": 13202447879, "name": null, "amenity": "bench", "man_made": null, "leisure": null, "playground": null, "memorial": null }, "geometry": { "type": "Point", "coordinates": [ -3.2290149, 51.695201 ] } }
]
}
