{
"type": "FeatureCollection",
"name": "a216a0432063_visibility",
"crs": { "type": "name", "properties": { "name": "urn:ogc:def:crs:OGC:1.3:CRS84" } },
"features": [
{ "type": "Feature", "properties": { "visible_points": 1, "total_points": 44, "visibility_pct": 2.2727272727272729 }, "geometry": { "type": "Point", "coordinates": [ -2.850226256437642, 51.579725036168007 ] } },
{ "type": "Feature", "properties": { "visible_points": 0, "total_points": 42, "visibility_pct": 0.0 }, "geometry": { "type": "Point", "coordinates": [ -2.850026311224531, 51.579726482981108 ] } },
{ "type": "Feature", "properties": { "visible_points": 1, "total_points": 50, "visibility_pct": 2.0 }, "geometry": { "type": "Point", "coordinates": [ -2.850328243044091, 51.579832197917959 ] } },
{ "type": "Feature", "properties": { "visible_points": 0, "total_points": 48, "visibility_pct": 0.0 }, "geometry": { "type": "Point", "coordinates": [ -2.850128297365546, 51.57983364490844 ] } },
{ "type": "Feature", "properties": { "visible_points": 1, "total_points": 56, "visibility_pct": 1.7857142857142856 }, "geometry": { "type": "Point", "coordinates": [ -2.850430230132692, 51.579939359573601 ] } },
{ "type": "Feature", "properties": { "visible_points": 0, "total_points": 55, "visibility_pct": 0.0 }, "geometry": { "type": "Point", "coordinates": [ -2.850230283988708, 51.579940806741462 ] } },
{ "type": "Feature", "properties": { "visible_points": 0, "total_points": 61, "visibility_pct": 0.0 }, "geometry": { "type": "Point", "coordinates": [ -2.850532217703448, 51.580046521134904 ] } },
{ "type": "Feature", "properties": { "visible_points": 0, "total_points": 61, "visibility_pct": 0.0 }, "geometry": { "type": "Point", "coordinates": [ -2.850332271094024, 51.580047968480152 ] } },
{ "type": "Feature", "properties": { "visible_points": 7, "total_points": 59, "visibility_pct": 11.864406779661017 }, "geometry": { "type": "Point", "coordinates": [ -2.850132324467878, 51.580049415484829 ] } },
{ "type": "Feature", "properties": { "visible_points": 2, "total_points": 60, "visibility_pct": 3.3333333333333335 }, "geometry": { "type": "Point", "coordinates": [ -2.850634205756362, 51.58015368260191 ] } },
{ "type": "Feature", "properties": { "visible_points": 2, "total_points": 61, "visibility_pct": 3.278688524590164 }, "geometry": { "type": "Point", "coordinates": [ -2.850434258681493, 51.580155130124545 ] } },
{ "type": "Feature", "properties": { "visible_points": 0, "total_points": 61, "visibility_pct": 0.0 }, "geometry": { "type": "Point", "coordinates": [ -2.850234311589908, 51.580156577306603 ] } },
{ "type": "Feature", "properties": { "visible_points": 5, "total_points": 55, "visibility_pct": 9.0909090909090917 }, "geometry": { "type": "Point", "coordinates": [ -2.850736194291441, 51.580260843974578 ] } },
{ "type": "Feature", "properties": { "visible_points": 2, "total_points": 57, "visibility_pct": 3.5087719298245612 }, "geometry": { "type": "Point", "coordinates": [ -2.850536246751128, 51.580262291674607 ] } },
{ "type": "Feature", "properties": { "visible_points": 0, "total_points": 58, "visibility_pct": 0.0 }, "geometry": { "type": "Point", "coordinates": [ -2.850336299194089, 51.580263739034038 ] } },
{ "type": "Feature", "properties": { "visible_points": 1, "total_points": 52, "visibility_pct": 1.9230769230769231 }, "geometry": { "type": "Point", "coordinates": [ -2.850638235302926, 51.580369453130338 ] } },
{ "type": "Feature", "properties": { "visible_points": 3, "total_points": 53, "visibility_pct": 5.6603773584905666 }, "geometry": { "type": "Point", "coordinates": [ -2.850438287280438, 51.580370900667184 ] } },
{ "type": "Feature", "properties": { "visible_points": 8, "total_points": 54, "visibility_pct": 14.814814814814813 }, "geometry": { "type": "Point", "coordinates": [ -2.850238339241228, 51.580372347863445 ] } },
{ "type": "Feature", "properties": { "visible_points": 4, "total_points": 46, "visibility_pct": 8.695652173913043 }, "geometry": { "type": "Point", "coordinates": [ -2.850740224336892, 51.580476614491786 ] } },
{ "type": "Feature", "properties": { "visible_points": 0, "total_points": 48, "visibility_pct": 0.0 }, "geometry": { "type": "Point", "coordinates": [ -2.850540275848955, 51.580478062206005 ] } },
{ "type": "Feature", "properties": { "visible_points": 0, "total_points": 49, "visibility_pct": 0.0 }, "geometry": { "type": "Point", "coordinates": [ -2.850340327344294, 51.580479509579646 ] } }
]
}
