{
"type": "FeatureCollection",
"name": "BLAGW_32_toilets",
"crs": { "type": "name", "properties": { "name": "urn:ogc:def:crs:OGC:1.3:CRS84" } },
"features": [
{ "type": "Feature", "properties": { "name": "Ebbw Vale Public Toilets", "payment_info": "Cost unknown", "accessible": "True", "radar": "Unknown", "women": "True", "men": "True", "baby_change": "Unknown", "Mon": "Unknown", "Tue": "Unknown", "Wed": "Unknown", "Thu": "Unknown", "Fri": "Unknown", "Sat": "Unknown", "Sun": "Unknown", "index_right": 25, "park_offical_id": "BLAGW_32" }, "geometry": { "type": "Point", "coordinates": [ -3.207449913, 51.779636797 ] } }
]
}
