{
"type": "FeatureCollection",
"name": "BLAGW_33_toilets",
"crs": { "type": "name", "properties": { "name": "urn:ogc:def:crs:OGC:1.3:CRS84" } },
"features": [
{ "type": "Feature", "properties": { "name": "Morrisons", "payment_info": "Free", "accessible": "Unknown", "radar": "Unknown", "women": "True", "men": "True", "baby_change": "Unknown", "Mon": "Unknown", "Tue": "Unknown", "Wed": "Unknown", "Thu": "Unknown", "Fri": "Unknown", "Sat": "Unknown", "Sun": "Unknown", "index_right": 26, "park_offical_id": "BLAGW_33" }, "geometry": { "type": "Point", "coordinates": [ -3.222577572, 51.793169238 ] } }
]
}
