{
"type": "FeatureCollection",
"name": "BLAGW_54_toilets",
"crs": { "type": "name", "properties": { "name": "urn:ogc:def:crs:OGC:1.3:CRS84" } },
"features": [
{ "type": "Feature", "properties": { "name": "Rhymney Library Hub", "payment_info": "Free", "accessible": "True", "radar": "False", "women": "True", "men": "True", "baby_change": "True", "Mon": "09:30-18:00", "Tue": "09:30-17:00", "Wed": "09:30-18:00", "Thu": "09:30-17:00", "Fri": "09:30-17:00", "Sat": "Closed", "Sun": "Closed", "index_right": 36, "park_offical_id": "BLAGW_54" }, "geometry": { "type": "Point", "coordinates": [ -3.283835737, 51.759378902 ] } },
{ "type": "Feature", "properties": { "name": "Cefn Golau Cemetery", "payment_info": "Cost unknown", "accessible": "False", "radar": "Unknown", "women": "Unknown", "men": "Unknown", "baby_change": "Unknown", "Mon": "Unknown", "Tue": "Unknown", "Wed": "Unknown", "Thu": "Unknown", "Fri": "Unknown", "Sat": "Unknown", "Sun": "Unknown", "index_right": 36, "park_offical_id": "BLAGW_54" }, "geometry": { "type": "Point", "coordinates": [ -3.2503438, 51.762786919 ] } }
]
}
