{
"type": "FeatureCollection",
"name": "NEWPO_57_toilets",
"crs": { "type": "name", "properties": { "name": "urn:ogc:def:crs:OGC:1.3:CRS84" } },
"features": [
{ "type": "Feature", "properties": { "name": "Morrisons Newport", "payment_info": "Free", "accessible": "True", "radar": "Unknown", "women": "True", "men": "True", "baby_change": "True", "Mon": "Unknown", "Tue": "Unknown", "Wed": "Unknown", "Thu": "Unknown", "Fri": "Unknown", "Sat": "Unknown", "Sun": "Unknown", "index_right": 70, "park_offical_id": "NEWPO_57" }, "geometry": { "type": "Point", "coordinates": [ -2.966722827, 51.57663139 ] } }
]
}
