{
"type": "FeatureCollection",
"name": "MONMO_214",
"crs": { "type": "name", "properties": { "name": "urn:ogc:def:crs:OGC:1.3:CRS84" } },
"features": [
{ "type": "Feature", "properties": { "osm_id": 13147059051, "name": null, "amenity": null, "man_made": null, "leisure": "picnic_table", "playground": null, "memorial": null }, "geometry": { "type": "Point", "coordinates": [ -2.7773803, 51.5851232 ] } },
{ "type": "Feature", "properties": { "osm_id": 13147059050, "name": null, "amenity": null, "man_made": null, "leisure": "picnic_table", "playground": null, "memorial": null }, "geometry": { "type": "Point", "coordinates": [ -2.7771981, 51.5851448 ] } },
{ "type": "Feature", "properties": { "osm_id": 13147059049, "name": null, "amenity": null, "man_made": null, "leisure": "picnic_table", "playground": null, "memorial": null }, "geometry": { "type": "Point", "coordinates": [ -2.7772016, 51.5852214 ] } },
{ "type": "Feature", "properties": { "osm_id": 13147059048, "name": null, "amenity": null, "man_made": null, "leisure": "picnic_table", "playground": null, "memorial": null }, "geometry": { "type": "Point", "coordinates": [ -2.7774157, 51.5852643 ] } }
]
}
