{
"type": "FeatureCollection",
"name": "2906522906fc_visibility",
"crs": { "type": "name", "properties": { "name": "urn:ogc:def:crs:OGC:1.3:CRS84" } },
"features": [
{ "type": "Feature", "properties": { "visible_points": 1, "total_points": 53, "visibility_pct": 1.8867924528301887 }, "geometry": { "type": "Point", "coordinates": [ -2.939017931933073, 51.579617763284077 ] } },
{ "type": "Feature", "properties": { "visible_points": 1, "total_points": 49, "visibility_pct": 2.0408163265306123 }, "geometry": { "type": "Point", "coordinates": [ -2.93881799131906, 51.579619361534263 ] } },
{ "type": "Feature", "properties": { "visible_points": 3, "total_points": 44, "visibility_pct": 6.8181818181818175 }, "geometry": { "type": "Point", "coordinates": [ -2.938618050686711, 51.579620959443723 ] } },
{ "type": "Feature", "properties": { "visible_points": 2, "total_points": 39, "visibility_pct": 5.1282051282051277 }, "geometry": { "type": "Point", "coordinates": [ -2.93841811003603, 51.579622557012414 ] } },
{ "type": "Feature", "properties": { "visible_points": 2, "total_points": 42, "visibility_pct": 4.7619047619047619 }, "geometry": { "type": "Point", "coordinates": [ -2.939719949338109, 51.579720049136974 ] } },
{ "type": "Feature", "properties": { "visible_points": 0, "total_points": 48, "visibility_pct": 0.0 }, "geometry": { "type": "Point", "coordinates": [ -2.939520008318897, 51.579721648580318 ] } },
{ "type": "Feature", "properties": { "visible_points": 2, "total_points": 54, "visibility_pct": 3.7037037037037033 }, "geometry": { "type": "Point", "coordinates": [ -2.939320067281333, 51.579723247682914 ] } },
{ "type": "Feature", "properties": { "visible_points": 4, "total_points": 54, "visibility_pct": 7.4074074074074066 }, "geometry": { "type": "Point", "coordinates": [ -2.939120126225431, 51.579724846444748 ] } },
{ "type": "Feature", "properties": { "visible_points": 3, "total_points": 53, "visibility_pct": 5.6603773584905666 }, "geometry": { "type": "Point", "coordinates": [ -2.938920185151187, 51.579726444865848 ] } },
{ "type": "Feature", "properties": { "visible_points": 3, "total_points": 48, "visibility_pct": 6.25 }, "geometry": { "type": "Point", "coordinates": [ -2.938720244058606, 51.579728042946172 ] } },
{ "type": "Feature", "properties": { "visible_points": 4, "total_points": 43, "visibility_pct": 9.3023255813953494 }, "geometry": { "type": "Point", "coordinates": [ -2.938520302947696, 51.579729640685777 ] } },
{ "type": "Feature", "properties": { "visible_points": 2, "total_points": 38, "visibility_pct": 5.2631578947368416 }, "geometry": { "type": "Point", "coordinates": [ -2.939822145489698, 51.579827131697279 ] } },
{ "type": "Feature", "properties": { "visible_points": 3, "total_points": 44, "visibility_pct": 6.8181818181818175 }, "geometry": { "type": "Point", "coordinates": [ -2.939622204010259, 51.579828731311537 ] } },
{ "type": "Feature", "properties": { "visible_points": 3, "total_points": 50, "visibility_pct": 6.0 }, "geometry": { "type": "Point", "coordinates": [ -2.939422262512473, 51.57983033058504 ] } },
{ "type": "Feature", "properties": { "visible_points": 7, "total_points": 54, "visibility_pct": 12.962962962962962 }, "geometry": { "type": "Point", "coordinates": [ -2.939222320996342, 51.579831929517781 ] } },
{ "type": "Feature", "properties": { "visible_points": 5, "total_points": 54, "visibility_pct": 9.2592592592592595 }, "geometry": { "type": "Point", "coordinates": [ -2.939022379461873, 51.579833528109766 ] } },
{ "type": "Feature", "properties": { "visible_points": 0, "total_points": 51, "visibility_pct": 0.0 }, "geometry": { "type": "Point", "coordinates": [ -2.938822437909054, 51.579835126361019 ] } },
{ "type": "Feature", "properties": { "visible_points": 1, "total_points": 46, "visibility_pct": 2.1739130434782608 }, "geometry": { "type": "Point", "coordinates": [ -2.938622496337917, 51.579836724271495 ] } },
{ "type": "Feature", "properties": { "visible_points": 0, "total_points": 40, "visibility_pct": 0.0 }, "geometry": { "type": "Point", "coordinates": [ -2.938422554748439, 51.579838321841223 ] } },
{ "type": "Feature", "properties": { "visible_points": 7, "total_points": 39, "visibility_pct": 17.948717948717949 }, "geometry": { "type": "Point", "coordinates": [ -2.93972440018019, 51.57993581395511 ] } },
{ "type": "Feature", "properties": { "visible_points": 3, "total_points": 45, "visibility_pct": 6.666666666666667 }, "geometry": { "type": "Point", "coordinates": [ -2.939524458222179, 51.579937413399499 ] } },
{ "type": "Feature", "properties": { "visible_points": 0, "total_points": 51, "visibility_pct": 0.0 }, "geometry": { "type": "Point", "coordinates": [ -2.939324516245819, 51.579939012503161 ] } }
]
}
